scr/Alu4.v
`timescale 1ns/1ps
module alu4(
  input  wire [3:0] a,
  input  wire [3:0] b,
  input  wire [2:0] op,   // 000 add, 001 sub, 010 mul, 011 NOR, 100 shl1(a)
  output reg  [3:0] y,
  output reg        overflow,
  output wire       zero
);
  wire [4:0] add5  = {1'b0,a} + {1'b0,b};
  wire [4:0] sub5  = {1'b0,a} + {1'b0,~b} + 5'b00001; // a - b = a + (~b + 1)
  wire [7:0] mul8  = a * b;
  wire [4:0] shl5a = {1'b0,a} << 1;

  always @* begin
    y = 4'h0;
    overflow = 1'b0;
    case (op)
      3'b000: begin // ADD
        y = add5[3:0];
        overflow = add5[4]; // carry
      end
      3'b001: begin // SUB (a - b)
        y = sub5[3:0];
        overflow = ~sub5[4]; // borrow
      end
      3'b010: begin // MUL
        y = mul8[3:0];
        overflow = |mul8[7:4];
      end
      3'b011: begin // NOR
        y = ~(a | b);
        overflow = 1'b0;
      end
      3'b100: begin // SHL1(a)
        y = shl5a[3:0];
        overflow = shl5a[4]; // bit expulsado
      end
      default: begin
        y = 4'h0;
        overflow = 1'b0;
      end
    endcase
  end

  assign zero = (y == 4'h0);

endmodule

scr/tb_alu4.v
`timescale 1ns/1ps
// Testbench para alu4.v — genera VCD para GTKWave
module tb_alu4;
  // Entradas
  reg  [3:0] a;
  reg  [3:0] b;
  reg  [2:0] op;
  // Salidas
  wire [3:0] y;
  wire       overflow;
  wire       zero;

  // DUT
  alu4 dut (
    .a(a),
    .b(b),
    .op(op),
    .y(y),
    .overflow(overflow),
    .zero(zero)
  );

  // Dump para GTKWave
  initial begin
    $dumpfile("alu4_tb.vcd");
    $dumpvars(0, tb_alu4);
  end

  // Estímulos
  task drive(input [3:0] aa, input [3:0] bb, input [2:0] oo);
    begin
      a  = aa;
      b  = bb;
      op = oo;
      #5; // tiempo de propagación
      $display("%0t ns | op=%b a=%h b=%h -> y=%h of=%b z=%b",
               $time, op, a, b, y, overflow, zero);
    end
  endtask

  initial begin
    a = 0; b = 0; op = 0;
    #1;

    // 000: ADD
    drive(4'h3, 4'h4, 3'b000); // 3 + 4 = 7
    drive(4'hF, 4'h1, 3'b000); // 15 + 1 = 0 con overflow

    // 001: SUB
    drive(4'h7, 4'h2, 3'b001); // 7 - 2 = 5
    drive(4'h0, 4'h1, 3'b001); // 0 - 1 = 15 con "préstamo" en overflow 

    // 010: MUL
    drive(4'h3, 4'h3, 3'b010); // 9
    drive(4'hF, 4'hF, 3'b010); // 

    // 011: NOR
    drive(4'h0, 4'h0, 3'b011); // NOR = 1111
    drive(4'hA, 4'h5, 3'b011); // NOR diversas combinaciones

    // 100: SHL1(a)
    drive(4'h7, 4'hX, 3'b100); // 0111<<1 = 1110
    drive(4'h8, 4'hX, 3'b100); // 1000<<1 = 0000 con overflow=1

    // Valores aleatorios
    repeat (10) begin
      drive($random, $random, $urandom_range(0,4)); // sólo ops definidas
    end

    #10;
    $finish;
  end
endmodule

scr/alu4_tb.vcd
$date
	Wed Oct 15 15:39:26 2025
$end
$version
	Icarus Verilog
$end
$timescale
	1ps
$end
$scope module tb_alu4 $end
$var wire 1 ! zero $end
$var wire 4 " y [3:0] $end
$var wire 1 # overflow $end
$var reg 4 $ a [3:0] $end
$var reg 4 % b [3:0] $end
$var reg 3 & op [2:0] $end
$scope module dut $end
$var wire 4 ' a [3:0] $end
$var wire 4 ( b [3:0] $end
$var wire 3 ) op [2:0] $end
$var wire 1 ! zero $end
$var wire 5 * sub5 [4:0] $end
$var wire 5 + shl5a [4:0] $end
$var wire 8 , mul8 [7:0] $end
$var wire 5 - add5 [4:0] $end
$var reg 1 # overflow $end
$var reg 4 . y [3:0] $end
$upscope $end
$scope task drive $end
$var reg 4 / aa [3:0] $end
$var reg 4 0 bb [3:0] $end
$var reg 3 1 oo [2:0] $end
$upscope $end
$upscope $end
$enddefinitions $end
$comment Show the parameter values. $end
$dumpall
$end
#0
$dumpvars
bx 1
bx 0
bx /
b0 .
b0 -
b0 ,
b0 +
b10000 *
b0 )
b0 (
b0 '
b0 &
b0 %
b0 $
0#
b0 "
1!
$end
#1000
0!
b111 "
b111 .
b110 +
b1100 ,
b100 %
b100 (
b111 -
b1111 *
b11 $
b11 '
b0 1
b100 0
b11 /
#6000
1#
1!
b0 "
b0 .
b11110 +
b1 %
b1 (
b10000 -
b11110 *
b1111 ,
b1111 $
b1111 '
b1 0
b1111 /
#11000
0!
b101 "
b101 .
0#
b1110 +
b1 &
b1 )
b10 %
b10 (
b1001 -
b10101 *
b1110 ,
b111 $
b111 '
b1 1
b10 0
b111 /
#16000
1#
0!
b1111 "
b1111 .
b0 +
b1 %
b1 (
b1 -
b1111 *
b0 ,
b0 $
b0 '
b1 0
b0 /
#21000
0#
0!
b1001 "
b1001 .
b110 +
b10 &
b10 )
b11 %
b11 (
b110 -
b10000 *
b1001 ,
b11 $
b11 '
b10 1
b11 0
b11 /
#26000
1#
0!
b1 "
b1 .
b11110 +
b1111 %
b1111 (
b11110 -
b10000 *
b11100001 ,
b1111 $
b1111 '
b1111 0
b1111 /
#31000
0#
0!
b1111 "
b1111 .
b0 +
b11 &
b11 )
b0 %
b0 (
b0 -
b10000 *
b0 ,
b0 $
b0 '
b11 1
b0 0
b0 /
#36000
1!
b0 "
b0 .
b10100 +
b110010 ,
b101 %
b101 (
b1111 -
b10101 *
b1010 $
b1010 '
b101 0
b1010 /
#41000
0!
b1110 "
b1110 .
b1110 +
b100 &
b100 )
bx %
bx (
bx -
bx *
bx ,
b111 $
b111 '
b100 1
bx 0
b111 /
#46000
1#
1!
b0 "
b0 .
b10000 +
b1000 $
b1000 '
b1000 /
#51000
b10011 *
0!
b100 "
b100 .
0#
b1000 +
b10 &
b10 )
b101 -
b100 ,
b1 %
b1 (
b100 $
b100 '
b10 1
b1 0
b100 /
#56000
0!
b110 "
b110 .
b10010 +
b1 &
b1 )
b11 %
b11 (
b1100 -
b10110 *
b11011 ,
b1001 $
b1001 '
b1 1
b11 0
b1001 /
#61000
1#
0!
b1010 "
b1010 .
b11010 +
b0 &
b0 )
b1101 %
b1101 (
b11010 -
b10000 *
b10101001 ,
b1101 $
b1101 '
b0 1
b1101 0
b1101 /
#66000
0#
0!
b111 "
b111 .
b1010 +
b10 %
b10 (
b111 -
b10011 *
b1010 ,
b101 $
b101 '
b10 0
b101 /
#71000
0!
b1101 "
b1101 .
b10 +
b10 &
b10 )
b1101 %
b1101 (
b1110 -
b100 *
b1101 ,
b1 $
b1 '
b10 1
b1101 0
b1 /
#76000
1!
b0 "
b0 .
b1100 +
b11 &
b11 )
b10011 -
b1001 *
b1001110 ,
b110 $
b110 '
b11 1
b110 /
#81000
1#
0!
b1001 "
b1001 .
b11010 +
b0 &
b0 )
b1100 %
b1100 (
b11001 -
b10001 *
b10011100 ,
b1101 $
b1101 '
b0 1
b1100 0
b1101 /
#86000
0#
0!
b1111 "
b1111 .
b10010 +
b110 %
b110 (
b1111 -
b10011 *
b110110 ,
b1001 $
b1001 '
b110 0
b1001 /
#91000
1#
0!
b10 "
b10 .
b1010 +
b10 &
b10 )
b1010 %
b1010 (
b1111 -
b1011 *
b110010 ,
b101 $
b101 '
b10 1
b1010 0
b101 /
#96000
b1110 *
1#
0!
b11 "
b11 .
b1100 -
b100011 ,
b111 %
b111 (
b111 0
